custom/FinaticServer.py
custom/__init__.py
custom/wrappers/brokers.py
custom/wrappers/company.py
custom/wrappers/session.py
generated/FinaticServer.py
generated/__init__.py
generated/api_client.py
generated/api_response.py
generated/config.py
generated/configuration.py
generated/exceptions.py
generated/rest.py
generated/types.py
generated/api/__init__.py
generated/api/brokers_api.py
generated/api/company_api.py
generated/api/session_api.py
generated/models/__init__.py
generated/models/account_status.py
generated/models/accountstatus0.py
generated/models/accounttype.py
generated/models/assettype.py
generated/models/availablebalance.py
generated/models/availabletowithdraw.py
generated/models/averagebuyprice.py
generated/models/averagefillprice.py
generated/models/averagesellprice.py
generated/models/balancetype.py
generated/models/broker_data_account_type_enum.py
generated/models/broker_data_asset_type_enum.py
generated/models/broker_data_order_side_enum.py
generated/models/broker_data_position_status_enum.py
generated/models/broker_info.py
generated/models/buyingpower.py
generated/models/cashbalance.py
generated/models/closedquantity.py
generated/models/closepriceavg.py
generated/models/commission.py
generated/models/commissionshare.py
generated/models/company_response.py
generated/models/costbasis.py
generated/models/costbasis1.py
generated/models/costbasiswithcommission.py
generated/models/costbasiswithcommission1.py
generated/models/currentbalance.py
generated/models/currentprice.py
generated/models/disconnect_action_result.py
generated/models/eventtype.py
generated/models/fdx_account_status.py
generated/models/fdx_account_type.py
generated/models/fdx_asset_type.py
generated/models/fdx_balance_type.py
generated/models/fdx_broker_account.py
generated/models/fdx_broker_balance.py
generated/models/fdx_broker_order.py
generated/models/fdx_broker_order_event.py
generated/models/fdx_broker_order_fill.py
generated/models/fdx_broker_order_group.py
finatic_server_python-0.9.4.dist-info/METADATA
finatic_server_python-0.9.4.dist-info/WHEEL
finatic_server_python-0.9.4.dist-info/licenses/LICENSE
finatic_server_python-0.9.4.dist-info/RECORD
