Metadata-Version: 2.4
Name: finatic-server-python
Version: 0.9.4
Summary: Python SDK for Finatic Server API
Project-URL: Homepage, https://github.com/FinaticORG/FinaticServerSDK-Python
Project-URL: Documentation, https://docs.finatic.com/python
Project-URL: Repository, https://github.com/FinaticORG/FinaticServerSDK-Python
Project-URL: Issues, https://github.com/FinaticORG/FinaticServerSDK-Python/issues
Author-email: Finatic <support@finatic.dev>
License: PROPRIETARY
License-File: LICENSE
Keywords: api,finance,finatic,sdk,trading
Classifier: Development Status :: 3 - Alpha
Classifier: Intended Audience :: Developers
Classifier: License :: Other/Proprietary License
Classifier: Programming Language :: Python :: 3
Classifier: Programming Language :: Python :: 3.8
Classifier: Programming Language :: Python :: 3.9
Classifier: Programming Language :: Python :: 3.10
Classifier: Programming Language :: Python :: 3.11
Classifier: Programming Language :: Python :: 3.12
Classifier: Topic :: Office/Business :: Financial
Classifier: Topic :: Software Development :: Libraries :: Python Modules
Requires-Python: >=3.9
Requires-Dist: aiohttp-retry>=2.9.1
Requires-Dist: aiohttp>=3.13.2
Requires-Dist: cachetools>=6.2.2
Requires-Dist: pydantic>=2.12.5
Requires-Dist: python-dateutil>=2.9.0.post0
Requires-Dist: structlog>=25.5.0
Requires-Dist: tenacity>=9.1.2
Requires-Dist: typing-extensions>=4.15.0
Requires-Dist: urllib3>=2.6.1
Provides-Extra: dev
Requires-Dist: black>=23.0.0; extra == 'dev'
Requires-Dist: flake8>=6.0.0; extra == 'dev'
Requires-Dist: isort>=5.12.0; extra == 'dev'
Requires-Dist: mypy>=1.0.0; extra == 'dev'
Requires-Dist: pre-commit>=3.0.0; extra == 'dev'
Requires-Dist: pytest-asyncio>=0.21.0; extra == 'dev'
Requires-Dist: pytest-cov>=4.0.0; extra == 'dev'
Requires-Dist: pytest>=7.0.0; extra == 'dev'
Requires-Dist: types-cachetools>=5.3.0; extra == 'dev'
Requires-Dist: types-python-dateutil>=2.8.0; extra == 'dev'
